mallet/__init__.py
mallet/class_dump.py
mallet/config.yml
mallet/helpers.py
mallet/loader.py
mallet/logger.py
mallet/type_cache.py
mallet/AFNetworking/__init__.py
mallet/AFNetworking/AFCompoundResponseSerializer.py
mallet/AFNetworking/AFHTTPRequestOperation.py
mallet/AFNetworking/AFHTTPRequestOperationManager.py
mallet/AFNetworking/AFHTTPRequestSerializer.py
mallet/AFNetworking/AFHTTPResponseSerializer.py
mallet/AFNetworking/AFHTTPSessionManager.py
mallet/AFNetworking/AFImageResponseSerializer.py
mallet/AFNetworking/AFJSONRequestSerializer.py
mallet/AFNetworking/AFJSONResponseSerializer.py
mallet/AFNetworking/AFNetworkActivityIndicatorManager.py
mallet/AFNetworking/AFNetworkReachabilityManager.py
mallet/AFNetworking/AFPropertyListRequestSerializer.py
mallet/AFNetworking/AFPropertyListResponseSerializer.py
mallet/AFNetworking/AFSecurityPolicy.py
mallet/AFNetworking/AFURLConnectionOperation.py
mallet/AFNetworking/AFURLSessionManager.py
mallet/AFNetworking/AFXMLDocumentResponseSerializer.py
mallet/AFNetworking/AFXMLParserResponseSerializer.py
mallet/AFNetworking/config.yml
mallet/AFNetworking/lldbinit
mallet/CFNetwork/__init__.py
mallet/CFNetwork/CFHTTPMessage.py
mallet/CFNetwork/CFURLRequest.py
mallet/CFNetwork/CFURLResponse.py
mallet/CFNetwork/config.yml
mallet/CFNetwork/HTTPHeaderDict.py
mallet/CFNetwork/lldbinit
mallet/CFNetwork/NSCFBackgroundDataTask.py
mallet/CFNetwork/NSCFBackgroundDownloadTask.py
mallet/CFNetwork/NSCFBackgroundSessionTask.py
mallet/CFNetwork/NSCFBackgroundUploadTask.py
mallet/CFNetwork/NSCFLocalDataTask.py
mallet/CFNetwork/NSCFLocalDownloadFile.py
mallet/CFNetwork/NSCFLocalDownloadTask.py
mallet/CFNetwork/NSCFLocalSessionTask.py
mallet/CFNetwork/NSCFLocalUploadTask.py
mallet/CFNetwork/NSHTTPCookieStorage.py
mallet/CFNetwork/NSHTTPURLResponse.py
mallet/CFNetwork/NSHTTPURLResponseInternal.py
mallet/CFNetwork/NSURLConnection.py
mallet/CFNetwork/NSURLConnectionInternal.py
mallet_lldb-1.0a2.dist-info/DESCRIPTION.rst
mallet_lldb-1.0a2.dist-info/METADATA
mallet_lldb-1.0a2.dist-info/metadata.json
mallet_lldb-1.0a2.dist-info/RECORD
mallet_lldb-1.0a2.dist-info/top_level.txt
mallet_lldb-1.0a2.dist-info/WHEEL
