Metadata-Version: 2.0
Name: mallet-lldb
Version: 1.0a2
Summary: LLDB additions for iOS project.
Home-page: https://github.com/bartoszj/Mallet
Author: Bartosz Janda
Author-email: UNKNOWN
License: MIT
Keywords: LLDB debugger development iOS summary
Platform: UNKNOWN
Classifier: Development Status :: 3 - Alpha
Classifier: Environment :: Console
Classifier: Environment :: MacOS X
Classifier: Environment :: Plugins
Classifier: Intended Audience :: Developers
Classifier: License :: OSI Approved :: MIT License
Classifier: Operating System :: MacOS
Classifier: Programming Language :: Python :: 2.7
Classifier: Topic :: Software Development :: Debuggers
Requires-Dist: PyYAML
Provides-Extra: dev
Requires-Dist: tabulate; extra == 'dev'
